{
  "001": {
    "name": "Bulbasaur",
    "type1": "Grass",
    "type2": "Poison"
  },
  "002": {
    "name": "Ivysaur",
    "type1": "Grass",
    "type2": "Poison"
  },
  "003": {
    "name": "Venusaur",
    "type1": "Grass",
    "type2": "Poison"
  },
  "004": {
    "name": "Charmander",
    "type1": "Fire"
  },
  "005": {
    "name": "Charmeleon",
    "type1": "Fire"
  },
  "006": {
    "name": "Charizard",
    "type1": "Fire",
    "type2": "Flying"
  },
  "007": {
    "name": "Squirtle",
    "type1": "Water"
  },
  "008": {
    "name": "Wartortle",
    "type1": "Water"
  },
  "009": {
    "name": "Blastoise",
    "type1": "Water"
  },
  "010": {
    "name": "Caterpie",
    "type1": "Bug"
  },
  "011": {
    "name": "Metapod",
    "type1": "Bug"
  },
  "012": {
    "name": "Butterfree",
    "type1": "Bug",
    "type2": "Flying"
  },
  "013": {
    "name": "Weedle",
    "type1": "Bug",
    "type2": "Poison"
  },
  "014": {
    "name": "Kakuna",
    "type1": "Bug",
    "type2": "Poison"
  },
  "015": {
    "name": "Beedrill",
    "type1": "Bug",
    "type2": "Poison"
  },
  "016": {
    "name": "Pidgey",
    "type1": "Normal",
    "type2": "Flying"
  },
  "017": {
    "name": "Pidgeotto",
    "type1": "Normal",
    "type2": "Flying"
  },
  "018": {
    "name": "Pidgeot",
    "type1": "Normal",
    "type2": "Flying"
  },
  "019": {
    "name": "Rattata",
    "type1": "Normal"
  },
  "020": {
    "name": "Raticate",
    "type1": "Normal"
  },
  "021": {
    "name": "Spearow",
    "type1": "Normal",
    "type2": "Flying"
  },
  "022": {
    "name": "Fearow",
    "type1": "Normal",
    "type2": "Flying"
  },
  "023": {
    "name": "Ekans",
    "type1": "Poison"
  },
  "024": {
    "name": "Arbok",
    "type1": "Poison"
  },
  "025": {
    "name": "Pikachu",
    "type1": "Electric"
  },
  "026": {
    "name": "Raichu",
    "type1": "Electric"
  },
  "027": {
    "name": "Sandshrew",
    "type1": "Ground"
  },
  "028": {
    "name": "Sandslash",
    "type1": "Ground"
  },
  "029": {
    "name": "Nidoran♀",
    "type1": "Poison"
  },
  "030": {
    "name": "Nidorina",
    "type1": "Poison"
  },
  "031": {
    "name": "Nidoqueen",
    "type1": "Poison",
    "type2": "Ground"
  },
  "032": {
    "name": "Nidoran♂",
    "type1": "Poison"
  },
  "033": {
    "name": "Nidorino",
    "type1": "Poison"
  },
  "034": {
    "name": "Nidoking",
    "type1": "Poison",
    "type2": "Ground"
  },
  "035": {
    "name": "Clefairy",
    "type1": "Normal"
  },
  "036": {
    "name": "Clefable",
    "type1": "Normal"
  },
  "037": {
    "name": "Vulpix",
    "type1": "Fire"
  },
  "038": {
    "name": "Ninetales",
    "type1": "Fire"
  },
  "039": {
    "name": "Jigglypuff",
    "type1": "Normal"
  },
  "040": {
    "name": "Wigglytuff",
    "type1": "Normal"
  },
  "041": {
    "name": "Zubat",
    "type1": "Poison",
    "type2": "Flying"
  },
  "042": {
    "name": "Golbat",
    "type1": "Poison",
    "type2": "Flying"
  },
  "043": {
    "name": "Oddish",
    "type1": "Grass",
    "type2": "Poison"
  },
  "044": {
    "name": "Gloom",
    "type1": "Grass",
    "type2": "Poison"
  },
  "045": {
    "name": "Vileplume",
    "type1": "Grass",
    "type2": "Poison"
  },
  "046": {
    "name": "Paras",
    "type1": "Bug",
    "type2": "Grass"
  },
  "047": {
    "name": "Parasect",
    "type1": "Bug",
    "type2": "Grass"
  },
  "048": {
    "name": "Venonat",
    "type1": "Bug",
    "type2": "Poison"
  },
  "049": {
    "name": "Venomoth",
    "type1": "Bug",
    "type2": "Poison"
  },
  "050": {
    "name": "Diglett",
    "type1": "Ground"
  },
  "051": {
    "name": "Dugtrio",
    "type1": "Ground"
  },
  "052": {
    "name": "Meowth",
    "type1": "Normal"
  },
  "053": {
    "name": "Persian",
    "type1": "Normal"
  },
  "054": {
    "name": "Psyduck",
    "type1": "Water"
  },
  "055": {
    "name": "Golduck",
    "type1": "Water"
  },
  "056": {
    "name": "Mankey",
    "type1": "Fighting"
  },
  "057": {
    "name": "Primeape",
    "type1": "Fighting"
  },
  "058": {
    "name": "Growlithe",
    "type1": "Fire"
  },
  "059": {
    "name": "Arcanine",
    "type1": "Fire"
  },
  "060": {
    "name": "Poliwag",
    "type1": "Water"
  },
  "061": {
    "name": "Poliwhirl",
    "type1": "Water"
  },
  "062": {
    "name": "Poliwrath",
    "type1": "Water",
    "type2": "Fighting"
  },
  "063": {
    "name": "Abra",
    "type1": "Psychic"
  },
  "064": {
    "name": "Kadabra",
    "type1": "Psychic"
  },
  "065": {
    "name": "Alakazam",
    "type1": "Psychic"
  },
  "066": {
    "name": "Machop",
    "type1": "Fighting"
  },
  "067": {
    "name": "Machoke",
    "type1": "Fighting"
  },
  "068": {
    "name": "Machamp",
    "type1": "Fighting"
  },
  "069": {
    "name": "Bellsprout",
    "type1": "Grass",
    "type2": "Poison"
  },
  "070": {
    "name": "Weepinbell",
    "type1": "Grass",
    "type2": "Poison"
  },
  "071": {
    "name": "Victreebel",
    "type1": "Grass",
    "type2": "Poison"
  },
  "072": {
    "name": "Tentacool",
    "type1": "Water",
    "type2": "Poison"
  },
  "073": {
    "name": "Tentacruel",
    "type1": "Water",
    "type2": "Poison"
  },
  "074": {
    "name": "Geodude",
    "type1": "Rock",
    "type2": "Ground"
  },
  "075": {
    "name": "Graveler",
    "type1": "Rock",
    "type2": "Ground"
  },
  "076": {
    "name": "Golem",
    "type1": "Rock",
    "type2": "Ground"
  },
  "077": {
    "name": "Ponyta",
    "type1": "Fire"
  },
  "078": {
    "name": "Rapidash",
    "type1": "Fire"
  },
  "079": {
    "name": "Slowpoke",
    "type1": "Water",
    "type2": "Psychic"
  },
  "080": {
    "name": "Slowbro",
    "type1": "Water",
    "type2": "Psychic"
  },
  "081": {
    "name": "Magnemite",
    "type1": "Electric",
    "type2": "Steel"
  },
  "082": {
    "name": "Magneton",
    "type1": "Electric",
    "type2": "Steel"
  },
  "083": {
    "name": "Farfetch'd",
    "type1": "Normal",
    "type2": "Flying"
  },
  "084": {
    "name": "Doduo",
    "type1": "Normal",
    "type2": "Flying"
  },
  "085": {
    "name": "Dodrio",
    "type1": "Normal",
    "type2": "Flying"
  },
  "086": {
    "name": "Seel",
    "type1": "Water"
  },
  "087": {
    "name": "Dewgong",
    "type1": "Water",
    "type2": "Ice"
  },
  "088": {
    "name": "Grimer",
    "type1": "Poison"
  },
  "089": {
    "name": "Muk",
    "type1": "Poison"
  },
  "090": {
    "name": "Shellder",
    "type1": "Water"
  },
  "091": {
    "name": "Cloyster",
    "type1": "Water",
    "type2": "Ice"
  },
  "092": {
    "name": "Gastly",
    "type1": "Ghost",
    "type2": "Poison"
  },
  "093": {
    "name": "Haunter",
    "type1": "Ghost",
    "type2": "Poison"
  },
  "094": {
    "name": "Gengar",
    "type1": "Ghost",
    "type2": "Poison"
  },
  "095": {
    "name": "Onix",
    "type1": "Rock",
    "type2": "Ground"
  },
  "096": {
    "name": "Drowzee",
    "type1": "Psychic"
  },
  "097": {
    "name": "Hypno",
    "type1": "Psychic"
  },
  "098": {
    "name": "Krabby",
    "type1": "Water"
  },
  "099": {
    "name": "Kingler",
    "type1": "Water"
  },
  "100": {
    "name": "Voltorb",
    "type1": "Electric"
  },
  "101": {
    "name": "Electrode",
    "type1": "Electric"
  },
  "102": {
    "name": "Exeggcute",
    "type1": "Grass",
    "type2": "Psychic"
  },
  "103": {
    "name": "Exeggutor",
    "type1": "Grass",
    "type2": "Psychic"
  },
  "104": {
    "name": "Cubone",
    "type1": "Ground"
  },
  "105": {
    "name": "Marowak",
    "type1": "Ground"
  },
  "106": {
    "name": "Hitmonlee",
    "type1": "Fighting"
  },
  "107": {
    "name": "Hitmonchan",
    "type1": "Fighting"
  },
  "108": {
    "name": "Lickitung",
    "type1": "Normal"
  },
  "109": {
    "name": "Koffing",
    "type1": "Poison"
  },
  "110": {
    "name": "Weezing",
    "type1": "Poison"
  },
  "111": {
    "name": "Rhyhorn",
    "type1": "Ground",
    "type2": "Rock"
  },
  "112": {
    "name": "Rhydon",
    "type1": "Ground",
    "type2": "Rock"
  },
  "113": {
    "name": "Chansey",
    "type1": "Normal"
  },
  "114": {
    "name": "Tangela",
    "type1": "Grass"
  },
  "115": {
    "name": "Kangaskhan",
    "type1": "Normal"
  },
  "116": {
    "name": "Horsea",
    "type1": "Water"
  },
  "117": {
    "name": "Seadra",
    "type1": "Water"
  },
  "118": {
    "name": "Goldeen",
    "type1": "Water"
  },
  "119": {
    "name": "Seaking",
    "type1": "Water"
  },
  "120": {
    "name": "Staryu",
    "type1": "Water"
  },
  "121": {
    "name": "Starmie",
    "type1": "Water",
    "type2": "Psychic"
  },
  "122": {
    "name": "Mr. Mime",
    "type1": "Psychic"
  },
  "123": {
    "name": "Scyther",
    "type1": "Bug",
    "type2": "Flying"
  },
  "124": {
    "name": "Jynx",
    "type1": "Ice",
    "type2": "Psychic"
  },
  "125": {
    "name": "Electabuzz",
    "type1": "Electric"
  },
  "126": {
    "name": "Magmar",
    "type1": "Fire"
  },
  "127": {
    "name": "Pinsir",
    "type1": "Bug"
  },
  "128": {
    "name": "Tauros",
    "type1": "Normal"
  },
  "129": {
    "name": "Magikarp",
    "type1": "Water"
  },
  "130": {
    "name": "Gyarados",
    "type1": "Water",
    "type2": "Flying"
  },
  "131": {
    "name": "Lapras",
    "type1": "Water",
    "type2": "Ice"
  },
  "132": {
    "name": "Ditto",
    "type1": "Normal"
  },
  "133": {
    "name": "Eevee",
    "type1": "Normal"
  },
  "134": {
    "name": "Vaporeon",
    "type1": "Water"
  },
  "135": {
    "name": "Jolteon",
    "type1": "Electric"
  },
  "136": {
    "name": "Flareon",
    "type1": "Fire"
  },
  "137": {
    "name": "Porygon",
    "type1": "Normal"
  },
  "138": {
    "name": "Omanyte",
    "type1": "Rock",
    "type2": "Water"
  },
  "139": {
    "name": "Omastar",
    "type1": "Rock",
    "type2": "Water"
  },
  "140": {
    "name": "Kabuto",
    "type1": "Rock",
    "type2": "Water"
  },
  "141": {
    "name": "Kabutops",
    "type1": "Rock",
    "type2": "Water"
  },
  "142": {
    "name": "Aerodactyl",
    "type1": "Rock",
    "type2": "Flying"
  },
  "143": {
    "name": "Snorlax",
    "type1": "Normal"
  },
  "144": {
    "name": "Articuno",
    "type1": "Ice",
    "type2": "Flying"
  },
  "145": {
    "name": "Zapdos",
    "type1": "Electric",
    "type2": "Flying"
  },
  "146": {
    "name": "Moltres",
    "type1": "Fire",
    "type2": "Flying"
  },
  "147": {
    "name": "Dratini",
    "type1": "Dragon"
  },
  "148": {
    "name": "Dragonair",
    "type1": "Dragon"
  },
  "149": {
    "name": "Dragonite",
    "type1": "Dragon",
    "type2": "Flying"
  },
  "150": {
    "name": "Mewtwo",
    "type1": "Psychic"
  },
  "151": {
    "name": "Mew",
    "type1": "Psychic"
  }
}
